diff_cover_shopee/__init__.py
diff_cover_shopee/command_runner.py
diff_cover_shopee/config_parser.py
diff_cover_shopee/diff_cover_tool.py
diff_cover_shopee/diff_quality_tool.py
diff_cover_shopee/diff_reporter.py
diff_cover_shopee/git_diff.py
diff_cover_shopee/git_path.py
diff_cover_shopee/hook.py
diff_cover_shopee/hookspecs.py
diff_cover_shopee/report_generator.py
diff_cover_shopee/snippets.py
diff_cover_shopee/templates/console_coverage_report.txt
diff_cover_shopee/templates/console_quality_report.txt
diff_cover_shopee/templates/external_style.css
diff_cover_shopee/templates/html_coverage_report.html
diff_cover_shopee/templates/html_quality_report.html
diff_cover_shopee/templates/markdown_coverage_report.md
diff_cover_shopee/templates/markdown_quality_report.md
diff_cover_shopee/templates/snippet_content.html
diff_cover_shopee/templates/snippet_content.md
diff_cover_shopee/templates/snippet_content.txt
diff_cover_shopee/templates/snippet_style.html
diff_cover_shopee/util.py
diff_cover_shopee/violationsreporters/__init__.py
diff_cover_shopee/violationsreporters/base.py
diff_cover_shopee/violationsreporters/java_violations_reporter.py
diff_cover_shopee/violationsreporters/violations_reporter.py
diff_cover_shopee-9.5.0.dist-info/LICENSE
diff_cover_shopee-9.5.0.dist-info/METADATA
diff_cover_shopee-9.5.0.dist-info/NOTICE
diff_cover_shopee-9.5.0.dist-info/WHEEL
diff_cover_shopee-9.5.0.dist-info/entry_points.txt
diff_cover_shopee-9.5.0.dist-info/RECORD
